amqencode/__init__.py
amqencode/__main__.py
amqencode/audio.py
amqencode/common.py
amqencode/encode.py
amqencode/mux.py
amqencode/video.py
amqencode-0.2.3.dist-info/LICENSE
amqencode-0.2.3.dist-info/METADATA
amqencode-0.2.3.dist-info/WHEEL
amqencode-0.2.3.dist-info/top_level.txt
amqencode-0.2.3.dist-info/RECORD
