Metadata-Version: 2.1
Name: amqencode
Version: 0.2.3
Summary: Encoding utility for Anime Music Quiz
Home-page: https://github.com/ayyu/amq-encoding
Author: ayyu
Author-email: 
Project-URL: Bug Tracker, https://github.com/ayyu/amq-encoding/issues
Classifier: Programming Language :: Python :: 3
Classifier: License :: OSI Approved :: MIT License
Classifier: Operating System :: OS Independent
Requires-Python: >=3.6
License-File: LICENSE
Requires-Dist: ffmpeg-python
